trade_lib/__init__.py
trade_lib/message.py
trade_lib/util.py
trade_lib/venus.py
trade_lib/weixin.py
trade_lib-0.2.1.dist-info/WHEEL
trade_lib-0.2.1.dist-info/METADATA
trade_lib-0.2.1.dist-info/RECORD
