Metadata-Version: 2.1
Name: trade-lib
Version: 0.2.1
Summary: 我的交易库
Author: oscar
Author-email: oscnet@163.com
Requires-Python: >=3.7,<4.0
Classifier: Programming Language :: Python :: 3
Classifier: Programming Language :: Python :: 3.7
Classifier: Programming Language :: Python :: 3.8
Classifier: Programming Language :: Python :: 3.9
Classifier: Programming Language :: Python :: 3.10
Classifier: Programming Language :: Python :: 3.11
Requires-Dist: aiofiles (>=23.1.0,<24.0.0)
Requires-Dist: aiohttp (>=3.8.3,<4.0.0)
Requires-Dist: pyyaml (>=6.0,<7.0)
